pgconnection/__init__.py
pgconnection/core.py
pgconnection/tests/__init__.py
pgconnection/tests/test_core.py
pgconnection/version.py
django_pgconnection-1.0.3.dist-info/LICENSE
django_pgconnection-1.0.3.dist-info/WHEEL
django_pgconnection-1.0.3.dist-info/METADATA
django_pgconnection-1.0.3.dist-info/RECORD
