Metadata-Version: 2.1
Name: django-pgconnection
Version: 1.0.3
Summary: Route postgres connections and hook into cursor execution
Home-page: https://github.com/Opus10/django-pgconnection
License: BSD-3-Clause
Author: Wes Kendall
Requires-Python: >=3.7.0,<4
Classifier: Framework :: Django
Classifier: Intended Audience :: Developers
Classifier: License :: OSI Approved :: BSD License
Classifier: Operating System :: OS Independent
Classifier: Programming Language :: Python
Classifier: Programming Language :: Python :: 3
Classifier: Programming Language :: Python :: 3 :: Only
Classifier: Programming Language :: Python :: 3.10
Classifier: Programming Language :: Python :: 3.7
Classifier: Programming Language :: Python :: 3.8
Classifier: Programming Language :: Python :: 3.9
Requires-Dist: django (>=2)
Requires-Dist: importlib_metadata (>=4); python_version >= "3.7" and python_version < "3.8"
Project-URL: Documentation, https://django-pgconnection.readthedocs.io
Project-URL: Repository, https://github.com/Opus10/django-pgconnection
